{
  "profile": {
    "username": "mr.zamaznoy",
    "full_name": "Alex Zamaznoy",
    "biography": "🔍  Truth is hidden in plain sight. I just help you see it.\nCollabs: @i_maryia",
    "followers": 592000,
    "followees": 9,
    "posts_count": 233,
    "is_verified": false,
    "is_private": false,
    "external_url": "",
    "profile_pic_url": ""
  },
  "posts": [],
  "stories": [],
  "total_fetched": 0,
  "metadata": {
    "platform": "instagram",
    "username": "mr.zamaznoy",
    "timestamp": "20250905_170532",
    "fetched_at": "2025-09-05T17:05:32.454532"
  }
}